kotti_audit/__init__.py
kotti_audit/fanstatic.py
kotti_audit/utils.py
kotti_audit/alembic/script.py.mako
kotti_audit/alembic/versions/.gitkeep
kotti_audit/locale/.gitkeep
kotti_audit/static/scripts.js
kotti_audit/static/scripts.min.js
kotti_audit/static/styles.css
kotti_audit/static/styles.min.css
kotti_audit/templates/audit-log.pt
kotti_audit/tests/conftest.py
kotti_audit/tests/test_functional.py
kotti_audit/tests/test_resources.py
kotti_audit/tests/test_view.py
kotti_audit/views/__init__.py
kotti_audit/views/view.py
kotti_audit-1.1.5.dist-info/LICENSE.txt
kotti_audit-1.1.5.dist-info/METADATA
kotti_audit-1.1.5.dist-info/WHEEL
kotti_audit-1.1.5.dist-info/entry_points.txt
kotti_audit-1.1.5.dist-info/top_level.txt
kotti_audit-1.1.5.dist-info/RECORD
